gitauthors/__init__.py
gitauthors/__version__.py
gitauthors/api.py
gitauthors/cli.py
gitauthors/gitauthors
gitauthors/gitauthors.py
gitauthors-0.1.4.dist-info/LICENSE.txt
gitauthors-0.1.4.dist-info/METADATA
gitauthors-0.1.4.dist-info/RECORD
gitauthors-0.1.4.dist-info/WHEEL
gitauthors-0.1.4.dist-info/entry_points.txt
gitauthors-0.1.4.dist-info/top_level.txt
