Metadata-Version: 2.1
Name: gitauthors
Version: 0.1.4
Summary: Inspect variables, expressions, and program execution with a single, simple function call.
Home-page: https://github.com/gruns/gitauthors
Author: Ansgar Grunseid
Author-email: grunseid@gmail.com
License: MIT
Platform: any
Classifier: License :: OSI Approved :: MIT License
Classifier: Natural Language :: English
Classifier: Intended Audience :: Developers
Classifier: Topic :: Software Development :: Libraries
Classifier: Development Status :: 4 - Beta
Classifier: Programming Language :: Python
Classifier: Programming Language :: Python :: 2
Classifier: Programming Language :: Python :: 2.7
Classifier: Programming Language :: Python :: 3
Classifier: Programming Language :: Python :: 3.4
Classifier: Programming Language :: Python :: 3.5
Classifier: Programming Language :: Python :: 3.6
Classifier: Programming Language :: Python :: Implementation :: PyPy
Classifier: Programming Language :: Python :: Implementation :: CPython
Requires-Dist: docopt (>=0.6.2)
Requires-Dist: dulwich (>=0.19.6)
